DeepRetail/__init__.py
DeepRetail/hierarchical.py
DeepRetail/version.py
DeepRetail/data/__init__.py
DeepRetail/data/casereaders.py
DeepRetail/data/dataloader.py
DeepRetail/evaluation/__init__.py
DeepRetail/evaluation/base.py
DeepRetail/evaluation/metrics.py
DeepRetail/exploratory/__init__.py
DeepRetail/exploratory/eda.py
DeepRetail/exploratory/visuals.py
DeepRetail/forecasting/__init__.py
DeepRetail/forecasting/ml.py
DeepRetail/forecasting/statistical.py
DeepRetail/forecasting/utils.py
DeepRetail/reconciliation/__init__.py
DeepRetail/reconciliation/cross_sectional.py
DeepRetail/reconciliation/cross_temporal.py
DeepRetail/reconciliation/temporal.py
DeepRetail/reconciliation/utils.py
DeepRetail/transformations/__init__.py
DeepRetail/transformations/decomposition.py
DeepRetail/transformations/formats.py
DeepRetail-0.0.9.dist-info/LICENSE
DeepRetail-0.0.9.dist-info/METADATA
DeepRetail-0.0.9.dist-info/WHEEL
DeepRetail-0.0.9.dist-info/top_level.txt
DeepRetail-0.0.9.dist-info/RECORD
