Metadata-Version: 2.1
Name: DeepRetail
Version: 0.0.9
Summary: Forecasting package for retail using Deep Learning AI.
Home-page: https://github.com/yForecasting/DeepRetail
Author: Yves R. Sagaert
Author-email: yves.r.sagaert@gmail.com
License: GNU GPLv3
Classifier: Development Status :: 4 - Beta
Classifier: License :: OSI Approved :: GNU General Public License v3 (GPLv3)
Classifier: Programming Language :: Python
Classifier: Programming Language :: Python :: 3.5
Classifier: Programming Language :: Python :: 3.6
Classifier: Topic :: Software Development :: Libraries
Classifier: Topic :: Software Development :: Libraries :: Python Modules
Classifier: Intended Audience :: Developers
Requires-Python: >=3.5
License-File: LICENSE
Requires-Dist: pandas
Requires-Dist: matplotlib
Requires-Dist: numpy
Requires-Dist: statsforecast
Requires-Dist: numba
Requires-Dist: openpyxl
Requires-Dist: tsfeatures
Requires-Dist: statsmodels
